codesweep/__init__.py
codesweep/_config/mypy.ini
codesweep/_config/ruff.toml
codesweep/_core.py
codesweep/_utils.py
codesweep/main.py
codesweep/py.typed
codesweep-0.0.2.dist-info/entry_points.txt
codesweep-0.0.2.dist-info/LICENSE
codesweep-0.0.2.dist-info/METADATA
codesweep-0.0.2.dist-info/WHEEL
codesweep-0.0.2.dist-info/RECORD
