Metadata-Version: 2.1
Name: codesweep
Version: 0.0.2
Summary: Streamline Code Maintenance: Instant Clean-Up and Rule Enforcement, Zero Configuration Required.
License: MIT
Author: joehaddad2000
Author-email: joehaddad129@gmail.com
Requires-Python: >=3.8,<4.0
Classifier: Development Status :: 2 - Pre-Alpha
Classifier: Intended Audience :: Developers
Classifier: License :: OSI Approved :: MIT License
Classifier: Operating System :: OS Independent
Classifier: Programming Language :: Python :: 3
Classifier: Programming Language :: Python :: 3.8
Classifier: Programming Language :: Python :: 3.9
Classifier: Programming Language :: Python :: 3.10
Classifier: Programming Language :: Python :: 3.11
Classifier: Programming Language :: Python :: Implementation :: CPython
Classifier: Programming Language :: Python :: Implementation :: PyPy
Classifier: Topic :: Software Development
Classifier: Topic :: Software Development :: Libraries
Classifier: Topic :: Software Development :: Libraries :: Python Modules
Classifier: Typing :: Typed
Requires-Dist: mypy (>=1.9.0,<2.0.0)
Requires-Dist: ruff (>=0.3.4,<0.4.0)
Requires-Dist: toml (>=0.10.2,<0.11.0)
Requires-Dist: typer (>=0.12.0,<0.13.0)
